AhronROC/__init__.py
AhronROC-1.2.dist-info/METADATA
AhronROC-1.2.dist-info/WHEEL
AhronROC-1.2.dist-info/top_level.txt
AhronROC-1.2.dist-info/RECORD
